crimson/auto_pydantic/__init__.py
crimson/auto_pydantic/generator.py
crimson/auto_pydantic/generator_model.py
crimson/auto_pydantic/validator.py
crimson_auto_pydantic-0.1.9.dist-info/LICENSE
crimson_auto_pydantic-0.1.9.dist-info/METADATA
crimson_auto_pydantic-0.1.9.dist-info/WHEEL
crimson_auto_pydantic-0.1.9.dist-info/top_level.txt
crimson_auto_pydantic-0.1.9.dist-info/RECORD
