Metadata-Version: 2.1
Name: crimson-auto-pydantic
Version: 0.1.9
Summary: Automatic Pydantic model generation and validation for function parameters and return types.
Author-email: Sisung Kim <sisung.kim1@gmail.com>
Project-URL: Homepage, https://github.com/crimson206/auto-pydantic
Project-URL: Bug Tracker, https://github.com/crimson206/auto-pydantic/issues
Classifier: Development Status :: 4 - Beta
Classifier: Programming Language :: Python :: 3
Classifier: Programming Language :: Python :: 3.9
Classifier: Programming Language :: Python :: 3.10
Classifier: Programming Language :: Python :: 3.11
Classifier: Intended Audience :: Developers
Classifier: Topic :: Software Development :: Libraries
Classifier: License :: OSI Approved :: MIT License
Classifier: Operating System :: OS Independent
Classifier: Typing :: Typed
Requires-Python: >=3.9
License-File: LICENSE
Requires-Dist: pydantic
Requires-Dist: crimson-code-extractor
Requires-Dist: crimson-ast-dev-tool
Requires-Dist: inflection
Requires-Dist: crimson-intelli-type
Requires-Dist: crimson-file-loader
